prefield/__init__.py
prefield/agent/Dockerfile
prefield/agent/README.md
prefield/agent/__init__.py
prefield/agent/start_agent.py
prefield/aws/__init__.py
prefield/aws/glue.py
prefield/aws/s3.py
prefield/aws/secrets.py
prefield/cli/__init__.py
prefield/cli/agent_commands.py
prefield/cli/flow_commands.py
prefield/cli/helpers.py
prefield/cli/main.py
prefield/cli/project_commands.py
prefield/datetime_util/__init__.py
prefield/datetime_util/dst.py
prefield/datetime_util/settlement.py
prefield/parsing/__init__.py
prefield/parsing/dataframe.py
prefield/parsing/xml.py
prefield/results/__init__.py
prefield/results/results.py
prefield/results/serializers.py
prefield/tasks/__init__.py
prefield/tasks/target_date.py
prefield-0.1.9.dist-info/entry_points.txt
prefield-0.1.9.dist-info/WHEEL
prefield-0.1.9.dist-info/METADATA
prefield-0.1.9.dist-info/RECORD
